django_unpoly/__init__.py
django_unpoly/cli.py
django_unpoly/exceptions.py
django_unpoly/middleware.py
django_unpoly/static/django_unpoly/up_djdt.js
django_unpoly/templates/up/form.up.html
django_unpoly/up.py
django_unpoly-0.2.0.dist-info/AUTHORS.md
django_unpoly-0.2.0.dist-info/LICENSE
django_unpoly-0.2.0.dist-info/METADATA
django_unpoly-0.2.0.dist-info/WHEEL
django_unpoly-0.2.0.dist-info/entry_points.txt
django_unpoly-0.2.0.dist-info/RECORD
