Metadata-Version: 2.1
Name: django-unpoly
Version: 0.2.0
Summary: Unpoly integration for Django.
Home-page: https://github.com/jwaschkau/django-unpoly
License: MIT
Author: Jannik Eilers
Author-email: j.waschkau@gmail.com
Requires-Python: >=3.8.0,<4.0
Classifier: Development Status :: 2 - Pre-Alpha
Classifier: Intended Audience :: Developers
Classifier: License :: OSI Approved :: MIT License
Classifier: Natural Language :: English
Classifier: Programming Language :: Python :: 3
Classifier: Programming Language :: Python :: 3.8
Classifier: Programming Language :: Python :: 3.9
Classifier: Programming Language :: Python :: 3.10
Classifier: Programming Language :: Python :: 3.11
Classifier: Programming Language :: Python :: 3.12
Provides-Extra: dev
Provides-Extra: doc
Provides-Extra: test
Requires-Dist: Django (>=3,<5)
Requires-Dist: black (>=24.4.1,<25.0.0) ; extra == "test"
Requires-Dist: docutils (!=0.21.post1)
Requires-Dist: fire (==0.4.0)
Requires-Dist: flake8 (==3.8.4) ; extra == "test"
Requires-Dist: flake8-docstrings (>=1.6,<2.0) ; extra == "test"
Requires-Dist: isort (==5.13.0) ; extra == "test"
Requires-Dist: mkdocs (>=1.6.0,<2.0.0) ; extra == "doc"
Requires-Dist: mkdocs-autorefs (>=1.0.1,<2.0.0) ; extra == "doc"
Requires-Dist: mkdocs-include-markdown-plugin (>=6.0.0,<7.0.0) ; extra == "doc"
Requires-Dist: mkdocs-material (>=9.0.0,<10.0.0) ; extra == "doc"
Requires-Dist: mkdocs-material-extensions (>=1.0.1,<2.0.0)
Requires-Dist: mkdocstrings (>=0.25.0,<0.26.0) ; extra == "doc"
Requires-Dist: pip (>=24.0,<25.0) ; extra == "dev"
Requires-Dist: pre-commit (>=2.12,<3.0) ; extra == "dev"
Requires-Dist: pytest (>=8.0,<9.0) ; extra == "test"
Requires-Dist: pytest-cov (>=5.0,<6.0) ; extra == "test"
Requires-Dist: toml (>=0.10,<0.11) ; extra == "dev"
Requires-Dist: tox (>=4.0,<5.0) ; extra == "dev"
Requires-Dist: twine (>=5.0,<6.0) ; extra == "dev"
Requires-Dist: virtualenv (>=20.26,<21.0) ; extra == "dev"
